tremulator/__init__.py
tremulator/emulator.py
tremulator/interpolator.py
tremulator/util.py
tremulator-0.0.4.dist-info/LICENSE
tremulator-0.0.4.dist-info/METADATA
tremulator-0.0.4.dist-info/WHEEL
tremulator-0.0.4.dist-info/top_level.txt
tremulator-0.0.4.dist-info/RECORD
