Metadata-Version: 2.1
Name: tremulator
Version: 0.0.4
Summary: A package to emulate expensive functions using Gaussian processes.
Home-page: https://github.com/StijnDebackere/tremulator
Author: Stijn Debackere
Author-email: debackere@strw.leidenuniv.nl
License: UNKNOWN
Platform: UNKNOWN
Classifier: Programming Language :: Python :: 3
Classifier: Programming Language :: Python :: 2
Classifier: License :: OSI Approved :: MIT License
Classifier: Operating System :: OS Independent
Requires-Dist: numpy
Requires-Dist: scipy
Requires-Dist: asdf
Requires-Dist: emcee
Requires-Dist: george
Requires-Dist: pyDOE
Requires-Dist: tqdm
